{
  "editable": true,
  "id": 3670604204601344,
  "links": [
    {
      "targetBlank": true,
      "title": "Executar Remediacao Conube",
      "url": "https://api.rpa4all.com/agents-api/conube/actions/run-remediation?notify_telegram=true"
    },
    {
      "targetBlank": true,
      "title": "Resumo Operacional (API)",
      "url": "https://api.rpa4all.com/agents-api/conube/dashboard/operational-summary"
    }
  ],
  "panels": [
    {
      "datasource": {
        "type": "prometheus",
        "uid": "dfc0w4yioe4u8e"
      },
      "fieldConfig": {
        "defaults": {
          "mappings": [
            {
              "options": {
                "0": {
                  "text": "Indisponivel"
                },
                "1": {
                  "text": "Operacional"
                }
              },
              "type": "value"
            }
          ],
          "thresholds": {
            "mode": "absolute",
            "steps": [
              {
                "color": "red"
              },
              {
                "color": "green",
                "value": 1
              }
            ]
          }
        }
      },
      "gridPos": {
        "h": 4,
        "w": 4,
        "x": 0,
        "y": 0
      },
      "id": 1,
      "options": {
        "colorMode": "background",
        "graphMode": "none",
        "reduceOptions": {
          "calcs": [
            "lastNotNull"
          ],
          "fields": "",
          "values": false
        },
        "textMode": "value"
      },
      "targets": [
        {
          "expr": "max(conube_exporter_up) or vector(0)",
          "format": "time_series",
          "instant": true,
          "refId": "A"
        }
      ],
      "title": "Exporter Conube",
      "type": "stat"
    },
    {
      "datasource": {
        "type": "prometheus",
        "uid": "dfc0w4yioe4u8e"
      },
      "fieldConfig": {
        "defaults": {
          "thresholds": {
            "mode": "absolute",
            "steps": [
              {
                "color": "green"
              },
              {
                "color": "orange",
                "value": 1
              },
              {
                "color": "red",
                "value": 3
              }
            ]
          }
        }
      },
      "gridPos": {
        "h": 4,
        "w": 4,
        "x": 4,
        "y": 0
      },
      "id": 2,
      "links": [
        {
          "targetBlank": true,
          "title": "Fechar periodos + remediar cliente",
          "url": "https://api.rpa4all.com/agents-api/conube/actions/run-remediation?run_client_tasks=true&notify_telegram=true"
        }
      ],
      "options": {
        "colorMode": "background",
        "graphMode": "none",
        "reduceOptions": {
          "calcs": [
            "lastNotNull"
          ],
          "fields": "",
          "values": false
        },
        "textMode": "value"
      },
      "targets": [
        {
          "expr": "max(conube_open_periods_total) or vector(0)",
          "format": "time_series",
          "instant": true,
          "refId": "A"
        }
      ],
      "title": "Periodos Abertos",
      "type": "stat"
    },
    {
      "datasource": {
        "type": "prometheus",
        "uid": "dfc0w4yioe4u8e"
      },
      "fieldConfig": {
        "defaults": {
          "thresholds": {
            "mode": "absolute",
            "steps": [
              {
                "color": "green"
              },
              {
                "color": "orange",
                "value": 1
              },
              {
                "color": "red",
                "value": 10
              }
            ]
          }
        }
      },
      "gridPos": {
        "h": 4,
        "w": 4,
        "x": 8,
        "y": 0
      },
      "id": 3,
      "options": {
        "colorMode": "background",
        "graphMode": "none",
        "reduceOptions": {
          "calcs": [
            "lastNotNull"
          ],
          "fields": "",
          "values": false
        },
        "textMode": "value"
      },
      "targets": [
        {
          "expr": "max(conube_pending_items_total) or vector(0)",
          "format": "time_series",
          "instant": true,
          "refId": "A"
        }
      ],
      "title": "Pendencias Totais",
      "type": "stat"
    },
    {
      "datasource": {
        "type": "prometheus",
        "uid": "dfc0w4yioe4u8e"
      },
      "fieldConfig": {
        "defaults": {
          "thresholds": {
            "mode": "absolute",
            "steps": [
              {
                "color": "green"
              },
              {
                "color": "orange",
                "value": 1
              },
              {
                "color": "red",
                "value": 5
              }
            ]
          }
        }
      },
      "gridPos": {
        "h": 4,
        "w": 4,
        "x": 12,
        "y": 0
      },
      "id": 4,
      "links": [
        {
          "targetBlank": true,
          "title": "Executar remediacao completa",
          "url": "https://api.rpa4all.com/agents-api/conube/actions/run-remediation?run_client_tasks=true&notify_telegram=true"
        }
      ],
      "options": {
        "colorMode": "background",
        "graphMode": "none",
        "reduceOptions": {
          "calcs": [
            "lastNotNull"
          ],
          "fields": "",
          "values": false
        },
        "textMode": "value"
      },
      "targets": [
        {
          "expr": "max(conube_overdue_items_total) or vector(0)",
          "format": "time_series",
          "instant": true,
          "refId": "A"
        }
      ],
      "title": "Pendencias em Atraso",
      "type": "stat"
    },
    {
      "datasource": {
        "type": "prometheus",
        "uid": "dfc0w4yioe4u8e"
      },
      "fieldConfig": {
        "defaults": {
          "mappings": [
            {
              "options": {
                "0": {
                  "text": "Nao"
                },
                "1": {
                  "text": "Sim"
                }
              },
              "type": "value"
            }
          ],
          "thresholds": {
            "mode": "absolute",
            "steps": [
              {
                "color": "green"
              },
              {
                "color": "red",
                "value": 1
              }
            ]
          }
        }
      },
      "gridPos": {
        "h": 4,
        "w": 4,
        "x": 16,
        "y": 0
      },
      "id": 5,
      "options": {
        "colorMode": "background",
        "graphMode": "none",
        "reduceOptions": {
          "calcs": [
            "lastNotNull"
          ],
          "fields": "",
          "values": false
        },
        "textMode": "value"
      },
      "targets": [
        {
          "expr": "max(conube_certificate_expired) or vector(0)",
          "format": "time_series",
          "instant": true,
          "refId": "A"
        }
      ],
      "title": "Certificado Expirado",
      "type": "stat"
    },
    {
      "datasource": {
        "type": "prometheus",
        "uid": "dfc0w4yioe4u8e"
      },
      "fieldConfig": {
        "defaults": {
          "mappings": [
            {
              "options": {
                "0": {
                  "text": "Nao"
                },
                "1": {
                  "text": "Sim"
                }
              },
              "type": "value"
            }
          ],
          "thresholds": {
            "mode": "absolute",
            "steps": [
              {
                "color": "green"
              },
              {
                "color": "red",
                "value": 1
              }
            ]
          }
        }
      },
      "gridPos": {
        "h": 4,
        "w": 4,
        "x": 20,
        "y": 0
      },
      "id": 6,
      "options": {
        "colorMode": "background",
        "graphMode": "none",
        "reduceOptions": {
          "calcs": [
            "lastNotNull"
          ],
          "fields": "",
          "values": false
        },
        "textMode": "value"
      },
      "targets": [
        {
          "expr": "max(conube_billing_blocked) or vector(0)",
          "format": "time_series",
          "instant": true,
          "refId": "A"
        }
      ],
      "title": "Faturamento Bloqueado",
      "type": "stat"
    },
    {
      "datasource": {
        "type": "prometheus",
        "uid": "dfc0w4yioe4u8e"
      },
      "fieldConfig": {
        "defaults": {
          "thresholds": {
            "mode": "absolute",
            "steps": [
              {
                "color": "green"
              },
              {
                "color": "orange",
                "value": 1
              },
              {
                "color": "red",
                "value": 2
              }
            ]
          }
        }
      },
      "gridPos": {
        "h": 4,
        "w": 4,
        "x": 0,
        "y": 4
      },
      "id": 10,
      "links": [
        {
          "targetBlank": true,
          "title": "Remediar pendencias do cliente",
          "url": "https://api.rpa4all.com/agents-api/conube/actions/run-remediation?run_client_tasks=true&close_periods_limit=1&notify_telegram=true"
        }
      ],
      "options": {
        "colorMode": "background",
        "graphMode": "none",
        "reduceOptions": {
          "calcs": [
            "lastNotNull"
          ],
          "fields": "",
          "values": false
        },
        "textMode": "value"
      },
      "targets": [
        {
          "expr": "max(conube_client_actionable_items_total) or vector(0)",
          "format": "time_series",
          "instant": true,
          "refId": "A"
        }
      ],
      "title": "Pendencias do Cliente",
      "type": "stat"
    },
    {
      "datasource": {
        "type": "prometheus",
        "uid": "dfc0w4yioe4u8e"
      },
      "fieldConfig": {
        "defaults": {
          "thresholds": {
            "mode": "absolute",
            "steps": [
              {
                "color": "green"
              },
              {
                "color": "orange",
                "value": 1
              },
              {
                "color": "red",
                "value": 10
              }
            ]
          }
        }
      },
      "gridPos": {
        "h": 4,
        "w": 4,
        "x": 4,
        "y": 4
      },
      "id": 11,
      "options": {
        "colorMode": "background",
        "graphMode": "none",
        "reduceOptions": {
          "calcs": [
            "lastNotNull"
          ],
          "fields": "",
          "values": false
        },
        "textMode": "value"
      },
      "targets": [
        {
          "expr": "max(conube_accountant_owned_items_total) or vector(0)",
          "format": "time_series",
          "instant": true,
          "refId": "A"
        }
      ],
      "title": "Pendencias do Contador",
      "type": "stat"
    },
    {
      "datasource": {
        "type": "prometheus",
        "uid": "dfc0w4yioe4u8e"
      },
      "fieldConfig": {
        "defaults": {
          "thresholds": {
            "mode": "absolute",
            "steps": [
              {
                "color": "green"
              },
              {
                "color": "orange",
                "value": 1
              },
              {
                "color": "red",
                "value": 5
              }
            ]
          }
        }
      },
      "gridPos": {
        "h": 8,
        "w": 16,
        "x": 8,
        "y": 4
      },
      "id": 7,
      "options": {
        "displayMode": "gradient",
        "orientation": "horizontal",
        "showUnfilled": true
      },
      "targets": [
        {
          "expr": "max(conube_open_periods_total) or vector(0)",
          "format": "time_series",
          "instant": true,
          "legendFormat": "Periodos abertos",
          "refId": "A"
        },
        {
          "expr": "max(conube_pending_items_total) or vector(0)",
          "format": "time_series",
          "instant": true,
          "legendFormat": "Pendencias totais",
          "refId": "B"
        },
        {
          "expr": "max(conube_overdue_items_total) or vector(0)",
          "format": "time_series",
          "instant": true,
          "legendFormat": "Pendencias em atraso",
          "refId": "C"
        }
      ],
      "title": "Risco Operacional",
      "type": "bargauge"
    },
    {
      "datasource": {
        "type": "prometheus",
        "uid": "dfc0w4yioe4u8e"
      },
      "gridPos": {
        "h": 8,
        "w": 12,
        "x": 0,
        "y": 8
      },
      "id": 8,
      "options": {
        "showHeader": true
      },
      "targets": [
        {
          "expr": "conube_financial_period_open == 1 or vector(0)",
          "format": "table",
          "instant": true,
          "refId": "A"
        }
      ],
      "title": "Competencias Abertas",
      "transformations": [
        {
          "id": "organize",
          "options": {
            "excludeByName": {
              "Time": true
            },
            "renameByName": {
              "Value": "aberto",
              "period": "competencia"
            }
          }
        }
      ],
      "type": "table"
    },
    {
      "datasource": {
        "type": "prometheus",
        "uid": "dfc0w4yioe4u8e"
      },
      "gridPos": {
        "h": 8,
        "w": 24,
        "x": 0,
        "y": 16
      },
      "id": 9,
      "options": {
        "showHeader": true
      },
      "targets": [
        {
          "expr": "conube_pending_item_overdue or vector(0)",
          "format": "table",
          "instant": true,
          "refId": "A"
        }
      ],
      "title": "Top Pendencias",
      "transformations": [
        {
          "id": "organize",
          "options": {
            "excludeByName": {
              "Time": true,
              "Value": true
            },
            "renameByName": {
              "source": "origem",
              "subject": "assunto"
            }
          }
        }
      ],
      "type": "table"
    }
  ],
  "refresh": "30s",
  "schemaVersion": 39,
  "tags": [
    "conube",
    "financeiro",
    "fiscal",
    "agent"
  ],
  "templating": {
    "list": []
  },
  "time": {
    "from": "now-30d",
    "to": "now"
  },
  "timezone": "browser",
  "title": "Conube Operational Monitor",
  "uid": "conube-operational",
  "version": 2
}
